{
    "data": {
        "getSearchFormImages": [
            {
                "imageInfoId": "398357045",
                "imageId": "398447115.00",
                "historyDate": null,
                "fileName": "00004_426_2_06570_2_0.jpg",
                "id": "IP2020LAP125163",
                "typeImage": 2,
                "sourceSystem": 11,
                "ely": 14,
                "municipality": 241,
                "region": 19,
                "contractArea": 1432,
                "road": 4,
                "roadSection": 426,
                "distance": 6558,
                "trackCode": 1,
                "givenCoord": null,
                "xGivenCoord": 386142,
                "yGivenCoord": 7300778,
                "zGivenCoord": null,
                "calcCoord": null,
                "xCalcCoord": null,
                "yCalcCoord": null,
                "zCalcCoord": null,
                "definition": "Infrap tiekuvat 2020",
                "roadAddressDirection": 2,
                "descDirection": 148,
                "side": 0,
                "getMovedCenterLine": null,
                "date": "2020-06-26 03:12:18",
                "publicity": 11,
                "organization": null,
                "lastName": null,
                "firstName": null,
                "trTerminationDate": null,
                "trChanges": null,
                "prStatus": 10,
                "prComplete": null,
                "vkmStatus": 10,
                "trStatus": 10,
                "userCreator": "U001502",
                "addedDate": "2020-07-30 12:35:47.0",
                "userChange": "KUVA-1124",
                "changeDate": "2020-07-30 12:35:47.0",
                "tlnumber": null,
                "mainImage": null,
                "track": null,
                "awsTunnus": "TIEKUVAT/TIE-4/TIEOSA-426/00004_426_2_06570_2_0-398447115.jpg",
                "awsUrl": "https://d28t77wkhtlfbl.cloudfront.net/smallpicture/TIEKUVAT/TIE-4/TIEOSA-426/00004_426_2_06570_2_0-398447115.jpg?token=r6AollNTyObOPrhYCvbe2g==:4B5cDhTrugHEZBWyVeFU9KFMI1v/JDNDXLN+fp4rR7iQWQElty29RWPkNX82oX7F+dBX5OnDWsKbpefQrhP3RA==",
                "awsThumbnailUrl": "https://d28t77wkhtlfbl.cloudfront.net/thumbnail/TIEKUVAT/TIE-4/TIEOSA-426/00004_426_2_06570_2_0-398447115.jpg?token=r6AollNTyObOPrhYCvbe2g==:4B5cDhTrugHEZBWyVeFU9KFMI1v/JDNDXLN+fp4rR7iQWQElty29RWPkNX82oX7F+dBX5OnDWsKbpefQrhP3RA==",
                "awsPictureUrl": "https://d28t77wkhtlfbl.cloudfront.net/picture/TIEKUVAT/TIE-4/TIEOSA-426/00004_426_2_06570_2_0-398447115.jpg?token=r6AollNTyObOPrhYCvbe2g==:4B5cDhTrugHEZBWyVeFU9KFMI1v/JDNDXLN+fp4rR7iQWQElty29RWPkNX82oX7F+dBX5OnDWsKbpefQrhP3RA==",
                "imagingJobId": "64",
                "displayType": 1,
                "stationId": null,
                "stationName": null,
                "greenBridgeId": null,
                "greenBridgeName": null,
                "sillariBridgeId": null,
                "sillariBridgeName": null,
                "__typename": "GQLImageInfo"
            },
            {
                "imageInfoId": "398357044",
                "imageId": "398447114.00",
                "historyDate": null,
                "fileName": "00004_426_2_06589_2_0.jpg",
                "id": "IP2020LAP125162",
                "typeImage": 2,
                "sourceSystem": 11,
                "ely": 14,
                "municipality": 241,
                "region": 19,
                "contractArea": 1432,
                "road": 4,
                "roadSection": 426,
                "distance": 6578,
                "trackCode": 1,
                "givenCoord": null,
                "xGivenCoord": 386133,
                "yGivenCoord": 7300795,
                "zGivenCoord": null,
                "calcCoord": null,
                "xCalcCoord": null,
                "yCalcCoord": null,
                "zCalcCoord": null,
                "definition": "Infrap tiekuvat 2020",
                "roadAddressDirection": 2,
                "descDirection": 147,
                "side": 0,
                "getMovedCenterLine": null,
                "date": "2020-06-26 03:12:17",
                "publicity": 11,
                "organization": null,
                "lastName": null,
                "firstName": null,
                "trTerminationDate": null,
                "trChanges": null,
                "prStatus": 10,
                "prComplete": null,
                "vkmStatus": 10,
                "trStatus": 10,
                "userCreator": "U001502",
                "addedDate": "2020-07-30 12:35:46.0",
                "userChange": "KUVA-1124",
                "changeDate": "2020-07-30 12:35:46.0",
                "tlnumber": null,
                "mainImage": null,
                "track": null,
                "awsTunnus": "TIEKUVAT/TIE-4/TIEOSA-426/00004_426_2_06589_2_0-398447114.jpg",
                "awsUrl": "https://d28t77wkhtlfbl.cloudfront.net/smallpicture/TIEKUVAT/TIE-4/TIEOSA-426/00004_426_2_06589_2_0-398447114.jpg?token=cQYxhIlzZ57NGvz3v2iTtA==:Lf/XBtetZGRI1IlOs5P4UJ8f8F7zwU05ni6TpMLdvHWAJjvmH4gt1Qce49lxmPOKLJmrTCvreMjspRDsnIkh6g==",
                "awsThumbnailUrl": "https://d28t77wkhtlfbl.cloudfront.net/thumbnail/TIEKUVAT/TIE-4/TIEOSA-426/00004_426_2_06589_2_0-398447114.jpg?token=cQYxhIlzZ57NGvz3v2iTtA==:Lf/XBtetZGRI1IlOs5P4UJ8f8F7zwU05ni6TpMLdvHWAJjvmH4gt1Qce49lxmPOKLJmrTCvreMjspRDsnIkh6g==",
                "awsPictureUrl": "https://d28t77wkhtlfbl.cloudfront.net/picture/TIEKUVAT/TIE-4/TIEOSA-426/00004_426_2_06589_2_0-398447114.jpg?token=cQYxhIlzZ57NGvz3v2iTtA==:Lf/XBtetZGRI1IlOs5P4UJ8f8F7zwU05ni6TpMLdvHWAJjvmH4gt1Qce49lxmPOKLJmrTCvreMjspRDsnIkh6g==",
                "imagingJobId": "64",
                "displayType": 1,
                "stationId": null,
                "stationName": null,
                "greenBridgeId": null,
                "greenBridgeName": null,
                "sillariBridgeId": null,
                "sillariBridgeName": null,
                "__typename": "GQLImageInfo"
            },
            {
                "imageInfoId": "398357043",
                "imageId": "398447113.00",
                "historyDate": null,
                "fileName": "00004_426_2_06608_2_0.jpg",
                "id": "IP2020LAP125161",
                "typeImage": 2,
                "sourceSystem": 11,
                "ely": 14,
                "municipality": 241,
                "region": 19,
                "contractArea": 1432,
                "road": 4,
                "roadSection": 426,
                "distance": 6597,
                "trackCode": 1,
                "givenCoord": null,
                "xGivenCoord": 386123,
                "yGivenCoord": 7300811,
                "zGivenCoord": null,
                "calcCoord": null,
                "xCalcCoord": null,
                "yCalcCoord": null,
                "zCalcCoord": null,
                "definition": "Infrap tiekuvat 2020",
                "roadAddressDirection": 2,
                "descDirection": 147,
                "side": 0,
                "getMovedCenterLine": null,
                "date": "2020-06-26 03:12:16",
                "publicity": 11,
                "organization": null,
                "lastName": null,
                "firstName": null,
                "trTerminationDate": null,
                "trChanges": null,
                "prStatus": 10,
                "prComplete": null,
                "vkmStatus": 10,
                "trStatus": 10,
                "userCreator": "U001502",
                "addedDate": "2020-07-30 12:35:46.0",
                "userChange": "KUVA-1124",
                "changeDate": "2020-07-30 12:35:46.0",
                "tlnumber": null,
                "mainImage": null,
                "track": null,
                "awsTunnus": "TIEKUVAT/TIE-4/TIEOSA-426/00004_426_2_06608_2_0-398447113.jpg",
                "awsUrl": "https://d28t77wkhtlfbl.cloudfront.net/smallpicture/TIEKUVAT/TIE-4/TIEOSA-426/00004_426_2_06608_2_0-398447113.jpg?token=a5zLQgeMYfZmwdGZfdnu2g==:TB88wUC1gCQDby754fjQABpAP3KT1wY/kxhlWPyTOBei7jsuKmWU9Av4VBsTrdZ+iLCPOkyZVOsrcTBvdiwK8w==",
                "awsThumbnailUrl": "https://d28t77wkhtlfbl.cloudfront.net/thumbnail/TIEKUVAT/TIE-4/TIEOSA-426/00004_426_2_06608_2_0-398447113.jpg?token=a5zLQgeMYfZmwdGZfdnu2g==:TB88wUC1gCQDby754fjQABpAP3KT1wY/kxhlWPyTOBei7jsuKmWU9Av4VBsTrdZ+iLCPOkyZVOsrcTBvdiwK8w==",
                "awsPictureUrl": "https://d28t77wkhtlfbl.cloudfront.net/picture/TIEKUVAT/TIE-4/TIEOSA-426/00004_426_2_06608_2_0-398447113.jpg?token=a5zLQgeMYfZmwdGZfdnu2g==:TB88wUC1gCQDby754fjQABpAP3KT1wY/kxhlWPyTOBei7jsuKmWU9Av4VBsTrdZ+iLCPOkyZVOsrcTBvdiwK8w==",
                "imagingJobId": "64",
                "displayType": 1,
                "stationId": null,
                "stationName": null,
                "greenBridgeId": null,
                "greenBridgeName": null,
                "sillariBridgeId": null,
                "sillariBridgeName": null,
                "__typename": "GQLImageInfo"
            },
            {
                "imageInfoId": "398357039",
                "imageId": "398447109.00",
                "historyDate": null,
                "fileName": "00004_426_2_06627_2_0.jpg",
                "id": "IP2020LAP125160",
                "typeImage": 2,
                "sourceSystem": 11,
                "ely": 14,
                "municipality": 241,
                "region": 19,
                "contractArea": 1432,
                "road": 4,
                "roadSection": 426,
                "distance": 6615,
                "trackCode": 1,
                "givenCoord": null,
                "xGivenCoord": 386114,
                "yGivenCoord": 7300827,
                "zGivenCoord": null,
                "calcCoord": null,
                "xCalcCoord": null,
                "yCalcCoord": null,
                "zCalcCoord": null,
                "definition": "Infrap tiekuvat 2020",
                "roadAddressDirection": 2,
                "descDirection": 147,
                "side": 0,
                "getMovedCenterLine": null,
                "date": "2020-06-26 03:12:15",
                "publicity": 11,
                "organization": null,
                "lastName": null,
                "firstName": null,
                "trTerminationDate": null,
                "trChanges": null,
                "prStatus": 10,
                "prComplete": null,
                "vkmStatus": 10,
                "trStatus": 10,
                "userCreator": "U001502",
                "addedDate": "2020-07-30 12:35:43.0",
                "userChange": "KUVA-1124",
                "changeDate": "2020-07-30 12:35:43.0",
                "tlnumber": null,
                "mainImage": null,
                "track": null,
                "awsTunnus": "TIEKUVAT/TIE-4/TIEOSA-426/00004_426_2_06627_2_0-398447109.jpg",
                "awsUrl": "https://d28t77wkhtlfbl.cloudfront.net/smallpicture/TIEKUVAT/TIE-4/TIEOSA-426/00004_426_2_06627_2_0-398447109.jpg?token=QY79WhI7zY7MB8B+XxTkVw==:v5ybB4Tx9+aseC2bK28R2JXiC3B7cD7ueoM/RT7ZXzCrXYQUgm77WVCHNxk9aLv5984SdX2i3lwjzN7s+SVGrA==",
                "awsThumbnailUrl": "https://d28t77wkhtlfbl.cloudfront.net/thumbnail/TIEKUVAT/TIE-4/TIEOSA-426/00004_426_2_06627_2_0-398447109.jpg?token=QY79WhI7zY7MB8B+XxTkVw==:v5ybB4Tx9+aseC2bK28R2JXiC3B7cD7ueoM/RT7ZXzCrXYQUgm77WVCHNxk9aLv5984SdX2i3lwjzN7s+SVGrA==",
                "awsPictureUrl": "https://d28t77wkhtlfbl.cloudfront.net/picture/TIEKUVAT/TIE-4/TIEOSA-426/00004_426_2_06627_2_0-398447109.jpg?token=QY79WhI7zY7MB8B+XxTkVw==:v5ybB4Tx9+aseC2bK28R2JXiC3B7cD7ueoM/RT7ZXzCrXYQUgm77WVCHNxk9aLv5984SdX2i3lwjzN7s+SVGrA==",
                "imagingJobId": "64",
                "displayType": 1,
                "stationId": null,
                "stationName": null,
                "greenBridgeId": null,
                "greenBridgeName": null,
                "sillariBridgeId": null,
                "sillariBridgeName": null,
                "__typename": "GQLImageInfo"
            },
            {
                "imageInfoId": "398357038",
                "imageId": "398447107.00",
                "historyDate": null,
                "fileName": "00004_426_2_06650_2_0.jpg",
                "id": "IP2020LAP125159",
                "typeImage": 2,
                "sourceSystem": 11,
                "ely": 14,
                "municipality": 241,
                "region": 19,
                "contractArea": 1432,
                "road": 4,
                "roadSection": 426,
                "distance": 6638,
                "trackCode": 1,
                "givenCoord": null,
                "xGivenCoord": 386102,
                "yGivenCoord": 7300847,
                "zGivenCoord": null,
                "calcCoord": null,
                "xCalcCoord": null,
                "yCalcCoord": null,
                "zCalcCoord": null,
                "definition": "Infrap tiekuvat 2020",
                "roadAddressDirection": 2,
                "descDirection": 146,
                "side": 0,
                "getMovedCenterLine": null,
                "date": "2020-06-26 03:12:14",
                "publicity": 11,
                "organization": null,
                "lastName": null,
                "firstName": null,
                "trTerminationDate": null,
                "trChanges": null,
                "prStatus": 10,
                "prComplete": null,
                "vkmStatus": 10,
                "trStatus": 10,
                "userCreator": "U001502",
                "addedDate": "2020-07-30 12:35:43.0",
                "userChange": "KUVA-1124",
                "changeDate": "2020-07-30 12:35:43.0",
                "tlnumber": null,
                "mainImage": null,
                "track": null,
                "awsTunnus": "TIEKUVAT/TIE-4/TIEOSA-426/00004_426_2_06650_2_0-398447107.jpg",
                "awsUrl": "https://d28t77wkhtlfbl.cloudfront.net/smallpicture/TIEKUVAT/TIE-4/TIEOSA-426/00004_426_2_06650_2_0-398447107.jpg?token=Dst+HDIEzs7Nt3TIDR2SXA==:+UOOaG0S9QNmMopCg6tzDDAuGyTvKzSypQ6QswqCI2Q2EJdgYN85JbGHtoru6rYiyOebaPwT6S7Y2hc6mxLOuQ==",
                "awsThumbnailUrl": "https://d28t77wkhtlfbl.cloudfront.net/thumbnail/TIEKUVAT/TIE-4/TIEOSA-426/00004_426_2_06650_2_0-398447107.jpg?token=Dst+HDIEzs7Nt3TIDR2SXA==:+UOOaG0S9QNmMopCg6tzDDAuGyTvKzSypQ6QswqCI2Q2EJdgYN85JbGHtoru6rYiyOebaPwT6S7Y2hc6mxLOuQ==",
                "awsPictureUrl": "https://d28t77wkhtlfbl.cloudfront.net/picture/TIEKUVAT/TIE-4/TIEOSA-426/00004_426_2_06650_2_0-398447107.jpg?token=Dst+HDIEzs7Nt3TIDR2SXA==:+UOOaG0S9QNmMopCg6tzDDAuGyTvKzSypQ6QswqCI2Q2EJdgYN85JbGHtoru6rYiyOebaPwT6S7Y2hc6mxLOuQ==",
                "imagingJobId": "64",
                "displayType": 1,
                "stationId": null,
                "stationName": null,
                "greenBridgeId": null,
                "greenBridgeName": null,
                "sillariBridgeId": null,
                "sillariBridgeName": null,
                "__typename": "GQLImageInfo"
            },
            {
                "imageInfoId": "398357036",
                "imageId": "398447105.00",
                "historyDate": null,
                "fileName": "00004_426_2_06669_2_0.jpg",
                "id": "IP2020LAP125158",
                "typeImage": 2,
                "sourceSystem": 11,
                "ely": 14,
                "municipality": 241,
                "region": 19,
                "contractArea": 1432,
                "road": 4,
                "roadSection": 426,
                "distance": 6657,
                "trackCode": 1,
                "givenCoord": null,
                "xGivenCoord": 386092,
                "yGivenCoord": 7300863,
                "zGivenCoord": null,
                "calcCoord": null,
                "xCalcCoord": null,
                "yCalcCoord": null,
                "zCalcCoord": null,
                "definition": "Infrap tiekuvat 2020",
                "roadAddressDirection": 2,
                "descDirection": 145,
                "side": 0,
                "getMovedCenterLine": null,
                "date": "2020-06-26 03:12:13",
                "publicity": 11,
                "organization": null,
                "lastName": null,
                "firstName": null,
                "trTerminationDate": null,
                "trChanges": null,
                "prStatus": 10,
                "prComplete": null,
                "vkmStatus": 10,
                "trStatus": 10,
                "userCreator": "U001502",
                "addedDate": "2020-07-30 12:35:42.0",
                "userChange": "KUVA-1124",
                "changeDate": "2020-07-30 12:35:42.0",
                "tlnumber": null,
                "mainImage": null,
                "track": null,
                "awsTunnus": "TIEKUVAT/TIE-4/TIEOSA-426/00004_426_2_06669_2_0-398447105.jpg",
                "awsUrl": "https://d28t77wkhtlfbl.cloudfront.net/smallpicture/TIEKUVAT/TIE-4/TIEOSA-426/00004_426_2_06669_2_0-398447105.jpg?token=QdwsE/OdtWnb/fUWg7KefQ==:jEa0IT7vkidOGwiS5KCAMJL918pnE9hlhLMUpHBXas6+xMvMNDrL/hAEASstoly1G1kejBa1rQhkSV3/5F8Tkw==",
                "awsThumbnailUrl": "https://d28t77wkhtlfbl.cloudfront.net/thumbnail/TIEKUVAT/TIE-4/TIEOSA-426/00004_426_2_06669_2_0-398447105.jpg?token=QdwsE/OdtWnb/fUWg7KefQ==:jEa0IT7vkidOGwiS5KCAMJL918pnE9hlhLMUpHBXas6+xMvMNDrL/hAEASstoly1G1kejBa1rQhkSV3/5F8Tkw==",
                "awsPictureUrl": "https://d28t77wkhtlfbl.cloudfront.net/picture/TIEKUVAT/TIE-4/TIEOSA-426/00004_426_2_06669_2_0-398447105.jpg?token=QdwsE/OdtWnb/fUWg7KefQ==:jEa0IT7vkidOGwiS5KCAMJL918pnE9hlhLMUpHBXas6+xMvMNDrL/hAEASstoly1G1kejBa1rQhkSV3/5F8Tkw==",
                "imagingJobId": "64",
                "displayType": 1,
                "stationId": null,
                "stationName": null,
                "greenBridgeId": null,
                "greenBridgeName": null,
                "sillariBridgeId": null,
                "sillariBridgeName": null,
                "__typename": "GQLImageInfo"
            },
            {
                "imageInfoId": "398357031",
                "imageId": "398447100.00",
                "historyDate": null,
                "fileName": "00004_426_2_06688_2_0.jpg",
                "id": "IP2020LAP125157",
                "typeImage": 2,
                "sourceSystem": 11,
                "ely": 14,
                "municipality": 241,
                "region": 19,
                "contractArea": 1432,
                "road": 4,
                "roadSection": 426,
                "distance": 6676,
                "trackCode": 1,
                "givenCoord": null,
                "xGivenCoord": 386082,
                "yGivenCoord": 7300879,
                "zGivenCoord": null,
                "calcCoord": null,
                "xCalcCoord": null,
                "yCalcCoord": null,
                "zCalcCoord": null,
                "definition": "Infrap tiekuvat 2020",
                "roadAddressDirection": 2,
                "descDirection": 145,
                "side": 0,
                "getMovedCenterLine": null,
                "date": "2020-06-26 03:12:12",
                "publicity": 11,
                "organization": null,
                "lastName": null,
                "firstName": null,
                "trTerminationDate": null,
                "trChanges": null,
                "prStatus": 10,
                "prComplete": null,
                "vkmStatus": 10,
                "trStatus": 10,
                "userCreator": "U001502",
                "addedDate": "2020-07-30 12:35:40.0",
                "userChange": "KUVA-1124",
                "changeDate": "2020-07-30 12:35:40.0",
                "tlnumber": null,
                "mainImage": null,
                "track": null,
                "awsTunnus": "TIEKUVAT/TIE-4/TIEOSA-426/00004_426_2_06688_2_0-398447100.jpg",
                "awsUrl": "https://d28t77wkhtlfbl.cloudfront.net/smallpicture/TIEKUVAT/TIE-4/TIEOSA-426/00004_426_2_06688_2_0-398447100.jpg?token=cNmIYEd9Hhy93KU/wx62Ag==:Jr/dscAPAUL1nf4zRXVUtB4nY0QMpDWMF5hwlnhjWdKFW3u+JXcSB+YhdKipGQdcX0AQ7udhV3ioqT0q4jTl1w==",
                "awsThumbnailUrl": "https://d28t77wkhtlfbl.cloudfront.net/thumbnail/TIEKUVAT/TIE-4/TIEOSA-426/00004_426_2_06688_2_0-398447100.jpg?token=cNmIYEd9Hhy93KU/wx62Ag==:Jr/dscAPAUL1nf4zRXVUtB4nY0QMpDWMF5hwlnhjWdKFW3u+JXcSB+YhdKipGQdcX0AQ7udhV3ioqT0q4jTl1w==",
                "awsPictureUrl": "https://d28t77wkhtlfbl.cloudfront.net/picture/TIEKUVAT/TIE-4/TIEOSA-426/00004_426_2_06688_2_0-398447100.jpg?token=cNmIYEd9Hhy93KU/wx62Ag==:Jr/dscAPAUL1nf4zRXVUtB4nY0QMpDWMF5hwlnhjWdKFW3u+JXcSB+YhdKipGQdcX0AQ7udhV3ioqT0q4jTl1w==",
                "imagingJobId": "64",
                "displayType": 1,
                "stationId": null,
                "stationName": null,
                "greenBridgeId": null,
                "greenBridgeName": null,
                "sillariBridgeId": null,
                "sillariBridgeName": null,
                "__typename": "GQLImageInfo"
            },
            {
                "imageInfoId": "398357029",
                "imageId": "398447098.00",
                "historyDate": null,
                "fileName": "00004_426_2_06707_2_0.jpg",
                "id": "IP2020LAP125156",
                "typeImage": 2,
                "sourceSystem": 11,
                "ely": 14,
                "municipality": 241,
                "region": 19,
                "contractArea": 1432,
                "road": 4,
                "roadSection": 426,
                "distance": 6697,
                "trackCode": 1,
                "givenCoord": null,
                "xGivenCoord": 386072,
                "yGivenCoord": 7300895,
                "zGivenCoord": null,
                "calcCoord": null,
                "xCalcCoord": null,
                "yCalcCoord": null,
                "zCalcCoord": null,
                "definition": "Infrap tiekuvat 2020",
                "roadAddressDirection": 2,
                "descDirection": 144,
                "side": 0,
                "getMovedCenterLine": null,
                "date": "2020-06-26 03:12:11",
                "publicity": 11,
                "organization": null,
                "lastName": null,
                "firstName": null,
                "trTerminationDate": null,
                "trChanges": null,
                "prStatus": 10,
                "prComplete": null,
                "vkmStatus": 10,
                "trStatus": 10,
                "userCreator": "U001502",
                "addedDate": "2020-07-30 12:35:39.0",
                "userChange": "KUVA-1124",
                "changeDate": "2020-07-30 12:35:39.0",
                "tlnumber": null,
                "mainImage": null,
                "track": null,
                "awsTunnus": "TIEKUVAT/TIE-4/TIEOSA-426/00004_426_2_06707_2_0-398447098.jpg",
                "awsUrl": "https://d28t77wkhtlfbl.cloudfront.net/smallpicture/TIEKUVAT/TIE-4/TIEOSA-426/00004_426_2_06707_2_0-398447098.jpg?token=9CRnd0Tnwqb8pPHs99UNPw==:uzgmQpWQG34b0TFOyxv4NJVyXzAZXqnKhAeqNCZT+mMVjr4tcHTYjjqhlPw09pkhuqv/Gel9+jqiaiH+Ez62cA==",
                "awsThumbnailUrl": "https://d28t77wkhtlfbl.cloudfront.net/thumbnail/TIEKUVAT/TIE-4/TIEOSA-426/00004_426_2_06707_2_0-398447098.jpg?token=9CRnd0Tnwqb8pPHs99UNPw==:uzgmQpWQG34b0TFOyxv4NJVyXzAZXqnKhAeqNCZT+mMVjr4tcHTYjjqhlPw09pkhuqv/Gel9+jqiaiH+Ez62cA==",
                "awsPictureUrl": "https://d28t77wkhtlfbl.cloudfront.net/picture/TIEKUVAT/TIE-4/TIEOSA-426/00004_426_2_06707_2_0-398447098.jpg?token=9CRnd0Tnwqb8pPHs99UNPw==:uzgmQpWQG34b0TFOyxv4NJVyXzAZXqnKhAeqNCZT+mMVjr4tcHTYjjqhlPw09pkhuqv/Gel9+jqiaiH+Ez62cA==",
                "imagingJobId": "64",
                "displayType": 1,
                "stationId": null,
                "stationName": null,
                "greenBridgeId": null,
                "greenBridgeName": null,
                "sillariBridgeId": null,
                "sillariBridgeName": null,
                "__typename": "GQLImageInfo"
            },
            {
                "imageInfoId": "398357027",
                "imageId": "398447097.00",
                "historyDate": null,
                "fileName": "00004_426_2_06729_2_0.jpg",
                "id": "IP2020LAP125155",
                "typeImage": 2,
                "sourceSystem": 11,
                "ely": 14,
                "municipality": 241,
                "region": 19,
                "contractArea": 1432,
                "road": 4,
                "roadSection": 426,
                "distance": 6719,
                "trackCode": 1,
                "givenCoord": null,
                "xGivenCoord": 386060,
                "yGivenCoord": 7300914,
                "zGivenCoord": null,
                "calcCoord": null,
                "xCalcCoord": null,
                "yCalcCoord": null,
                "zCalcCoord": null,
                "definition": "Infrap tiekuvat 2020",
                "roadAddressDirection": 2,
                "descDirection": 143,
                "side": 0,
                "getMovedCenterLine": null,
                "date": "2020-06-26 03:12:10",
                "publicity": 11,
                "organization": null,
                "lastName": null,
                "firstName": null,
                "trTerminationDate": null,
                "trChanges": null,
                "prStatus": 10,
                "prComplete": null,
                "vkmStatus": 10,
                "trStatus": 10,
                "userCreator": "U001502",
                "addedDate": "2020-07-30 12:35:39.0",
                "userChange": "KUVA-1124",
                "changeDate": "2020-07-30 12:35:39.0",
                "tlnumber": null,
                "mainImage": null,
                "track": null,
                "awsTunnus": "TIEKUVAT/TIE-4/TIEOSA-426/00004_426_2_06729_2_0-398447097.jpg",
                "awsUrl": "https://d28t77wkhtlfbl.cloudfront.net/smallpicture/TIEKUVAT/TIE-4/TIEOSA-426/00004_426_2_06729_2_0-398447097.jpg?token=v+n173u8xCLCij/noVnA/g==:z73ScVHxlULGef+Gdxpu/IzathkCNvjWDcV5Ie9g7JS7NpYhI1oispqoInnTGiRcpVZi5iowEAv2UnHklZRIoQ==",
                "awsThumbnailUrl": "https://d28t77wkhtlfbl.cloudfront.net/thumbnail/TIEKUVAT/TIE-4/TIEOSA-426/00004_426_2_06729_2_0-398447097.jpg?token=v+n173u8xCLCij/noVnA/g==:z73ScVHxlULGef+Gdxpu/IzathkCNvjWDcV5Ie9g7JS7NpYhI1oispqoInnTGiRcpVZi5iowEAv2UnHklZRIoQ==",
                "awsPictureUrl": "https://d28t77wkhtlfbl.cloudfront.net/picture/TIEKUVAT/TIE-4/TIEOSA-426/00004_426_2_06729_2_0-398447097.jpg?token=v+n173u8xCLCij/noVnA/g==:z73ScVHxlULGef+Gdxpu/IzathkCNvjWDcV5Ie9g7JS7NpYhI1oispqoInnTGiRcpVZi5iowEAv2UnHklZRIoQ==",
                "imagingJobId": "64",
                "displayType": 1,
                "stationId": null,
                "stationName": null,
                "greenBridgeId": null,
                "greenBridgeName": null,
                "sillariBridgeId": null,
                "sillariBridgeName": null,
                "__typename": "GQLImageInfo"
            },
            {
                "imageInfoId": "398357021",
                "imageId": "398447091.00",
                "historyDate": null,
                "fileName": "00004_426_2_06748_2_0.jpg",
                "id": "IP2020LAP125154",
                "typeImage": 2,
                "sourceSystem": 11,
                "ely": 14,
                "municipality": 241,
                "region": 19,
                "contractArea": 1432,
                "road": 4,
                "roadSection": 426,
                "distance": 6738,
                "trackCode": 1,
                "givenCoord": null,
                "xGivenCoord": 386049,
                "yGivenCoord": 7300929,
                "zGivenCoord": null,
                "calcCoord": null,
                "xCalcCoord": null,
                "yCalcCoord": null,
                "zCalcCoord": null,
                "definition": "Infrap tiekuvat 2020",
                "roadAddressDirection": 2,
                "descDirection": 142,
                "side": 0,
                "getMovedCenterLine": null,
                "date": "2020-06-26 03:12:09",
                "publicity": 11,
                "organization": null,
                "lastName": null,
                "firstName": null,
                "trTerminationDate": null,
                "trChanges": null,
                "prStatus": 10,
                "prComplete": null,
                "vkmStatus": 10,
                "trStatus": 10,
                "userCreator": "U001502",
                "addedDate": "2020-07-30 12:35:37.0",
                "userChange": "KUVA-1124",
                "changeDate": "2020-07-30 12:35:37.0",
                "tlnumber": null,
                "mainImage": null,
                "track": null,
                "awsTunnus": "TIEKUVAT/TIE-4/TIEOSA-426/00004_426_2_06748_2_0-398447091.jpg",
                "awsUrl": "https://d28t77wkhtlfbl.cloudfront.net/smallpicture/TIEKUVAT/TIE-4/TIEOSA-426/00004_426_2_06748_2_0-398447091.jpg?token=Tw8DXDmoLrmLv1yaYRZJ6g==:SSpETJuXmUSKsLCGZ1b+5+DydN1rB5vzq8zA4f8W8XqeyMYtuKq7WkPw72IT/aFDReEDOGx3je46yJAPqHMtBw==",
                "awsThumbnailUrl": "https://d28t77wkhtlfbl.cloudfront.net/thumbnail/TIEKUVAT/TIE-4/TIEOSA-426/00004_426_2_06748_2_0-398447091.jpg?token=Tw8DXDmoLrmLv1yaYRZJ6g==:SSpETJuXmUSKsLCGZ1b+5+DydN1rB5vzq8zA4f8W8XqeyMYtuKq7WkPw72IT/aFDReEDOGx3je46yJAPqHMtBw==",
                "awsPictureUrl": "https://d28t77wkhtlfbl.cloudfront.net/picture/TIEKUVAT/TIE-4/TIEOSA-426/00004_426_2_06748_2_0-398447091.jpg?token=Tw8DXDmoLrmLv1yaYRZJ6g==:SSpETJuXmUSKsLCGZ1b+5+DydN1rB5vzq8zA4f8W8XqeyMYtuKq7WkPw72IT/aFDReEDOGx3je46yJAPqHMtBw==",
                "imagingJobId": "64",
                "displayType": 1,
                "stationId": null,
                "stationName": null,
                "greenBridgeId": null,
                "greenBridgeName": null,
                "sillariBridgeId": null,
                "sillariBridgeName": null,
                "__typename": "GQLImageInfo"
            },
            {
                "imageInfoId": "398357019",
                "imageId": "398447089.00",
                "historyDate": null,
                "fileName": "00004_426_2_06771_2_0.jpg",
                "id": "IP2020LAP125153",
                "typeImage": 2,
                "sourceSystem": 11,
                "ely": 14,
                "municipality": 241,
                "region": 19,
                "contractArea": 1432,
                "road": 4,
                "roadSection": 426,
                "distance": 6761,
                "trackCode": 1,
                "givenCoord": null,
                "xGivenCoord": 386036,
                "yGivenCoord": 7300948,
                "zGivenCoord": null,
                "calcCoord": null,
                "xCalcCoord": null,
                "yCalcCoord": null,
                "zCalcCoord": null,
                "definition": "Infrap tiekuvat 2020",
                "roadAddressDirection": 2,
                "descDirection": 142,
                "side": 0,
                "getMovedCenterLine": null,
                "date": "2020-06-26 03:12:08",
                "publicity": 11,
                "organization": null,
                "lastName": null,
                "firstName": null,
                "trTerminationDate": null,
                "trChanges": null,
                "prStatus": 10,
                "prComplete": null,
                "vkmStatus": 10,
                "trStatus": 10,
                "userCreator": "U001502",
                "addedDate": "2020-07-30 12:35:36.0",
                "userChange": "KUVA-1124",
                "changeDate": "2020-07-30 12:35:36.0",
                "tlnumber": null,
                "mainImage": null,
                "track": null,
                "awsTunnus": "TIEKUVAT/TIE-4/TIEOSA-426/00004_426_2_06771_2_0-398447089.jpg",
                "awsUrl": "https://d28t77wkhtlfbl.cloudfront.net/smallpicture/TIEKUVAT/TIE-4/TIEOSA-426/00004_426_2_06771_2_0-398447089.jpg?token=F+S6UR88TJoYWVdRLazGKg==:u1YrGV2tHJBbdb9k2yju5Ajc4GfwHfKpK8wCU+Qk62uYpN/wKWHa/FDP0fZmgCIqkObK2sB7a+waQtv+mQDL9w==",
                "awsThumbnailUrl": "https://d28t77wkhtlfbl.cloudfront.net/thumbnail/TIEKUVAT/TIE-4/TIEOSA-426/00004_426_2_06771_2_0-398447089.jpg?token=F+S6UR88TJoYWVdRLazGKg==:u1YrGV2tHJBbdb9k2yju5Ajc4GfwHfKpK8wCU+Qk62uYpN/wKWHa/FDP0fZmgCIqkObK2sB7a+waQtv+mQDL9w==",
                "awsPictureUrl": "https://d28t77wkhtlfbl.cloudfront.net/picture/TIEKUVAT/TIE-4/TIEOSA-426/00004_426_2_06771_2_0-398447089.jpg?token=F+S6UR88TJoYWVdRLazGKg==:u1YrGV2tHJBbdb9k2yju5Ajc4GfwHfKpK8wCU+Qk62uYpN/wKWHa/FDP0fZmgCIqkObK2sB7a+waQtv+mQDL9w==",
                "imagingJobId": "64",
                "displayType": 1,
                "stationId": null,
                "stationName": null,
                "greenBridgeId": null,
                "greenBridgeName": null,
                "sillariBridgeId": null,
                "sillariBridgeName": null,
                "__typename": "GQLImageInfo"
            },
            {
                "imageInfoId": "398357018",
                "imageId": "398447088.00",
                "historyDate": null,
                "fileName": "00004_426_2_06790_2_0.jpg",
                "id": "IP2020LAP125152",
                "typeImage": 2,
                "sourceSystem": 11,
                "ely": 14,
                "municipality": 241,
                "region": 19,
                "contractArea": 1432,
                "road": 4,
                "roadSection": 426,
                "distance": 6779,
                "trackCode": 1,
                "givenCoord": null,
                "xGivenCoord": 386025,
                "yGivenCoord": 7300963,
                "zGivenCoord": null,
                "calcCoord": null,
                "xCalcCoord": null,
                "yCalcCoord": null,
                "zCalcCoord": null,
                "definition": "Infrap tiekuvat 2020",
                "roadAddressDirection": 2,
                "descDirection": 141,
                "side": 0,
                "getMovedCenterLine": null,
                "date": "2020-06-26 03:12:07",
                "publicity": 11,
                "organization": null,
                "lastName": null,
                "firstName": null,
                "trTerminationDate": null,
                "trChanges": null,
                "prStatus": 10,
                "prComplete": null,
                "vkmStatus": 10,
                "trStatus": 10,
                "userCreator": "U001502",
                "addedDate": "2020-07-30 12:35:36.0",
                "userChange": "KUVA-1124",
                "changeDate": "2020-07-30 12:35:36.0",
                "tlnumber": null,
                "mainImage": null,
                "track": null,
                "awsTunnus": "TIEKUVAT/TIE-4/TIEOSA-426/00004_426_2_06790_2_0-398447088.jpg",
                "awsUrl": "https://d28t77wkhtlfbl.cloudfront.net/smallpicture/TIEKUVAT/TIE-4/TIEOSA-426/00004_426_2_06790_2_0-398447088.jpg?token=Io3N/XgAJq7/izCrOKokOA==:okNwZxBdxdtD+qmmapnNe6p8WBWTs014mwCEUsM7600/PATW71tInO13NHc134Reh0+/DQFpnshhGvuoQrU9jQ==",
                "awsThumbnailUrl": "https://d28t77wkhtlfbl.cloudfront.net/thumbnail/TIEKUVAT/TIE-4/TIEOSA-426/00004_426_2_06790_2_0-398447088.jpg?token=Io3N/XgAJq7/izCrOKokOA==:okNwZxBdxdtD+qmmapnNe6p8WBWTs014mwCEUsM7600/PATW71tInO13NHc134Reh0+/DQFpnshhGvuoQrU9jQ==",
                "awsPictureUrl": "https://d28t77wkhtlfbl.cloudfront.net/picture/TIEKUVAT/TIE-4/TIEOSA-426/00004_426_2_06790_2_0-398447088.jpg?token=Io3N/XgAJq7/izCrOKokOA==:okNwZxBdxdtD+qmmapnNe6p8WBWTs014mwCEUsM7600/PATW71tInO13NHc134Reh0+/DQFpnshhGvuoQrU9jQ==",
                "imagingJobId": "64",
                "displayType": 1,
                "stationId": null,
                "stationName": null,
                "greenBridgeId": null,
                "greenBridgeName": null,
                "sillariBridgeId": null,
                "sillariBridgeName": null,
                "__typename": "GQLImageInfo"
            },
            {
                "imageInfoId": "398357012",
                "imageId": "398447082.00",
                "historyDate": null,
                "fileName": "00004_426_2_06809_2_0.jpg",
                "id": "IP2020LAP125151",
                "typeImage": 2,
                "sourceSystem": 11,
                "ely": 14,
                "municipality": 241,
                "region": 19,
                "contractArea": 1432,
                "road": 4,
                "roadSection": 426,
                "distance": 6798,
                "trackCode": 1,
                "givenCoord": null,
                "xGivenCoord": 386014,
                "yGivenCoord": 7300979,
                "zGivenCoord": null,
                "calcCoord": null,
                "xCalcCoord": null,
                "yCalcCoord": null,
                "zCalcCoord": null,
                "definition": "Infrap tiekuvat 2020",
                "roadAddressDirection": 2,
                "descDirection": 142,
                "side": 0,
                "getMovedCenterLine": null,
                "date": "2020-06-26 03:12:06",
                "publicity": 11,
                "organization": null,
                "lastName": null,
                "firstName": null,
                "trTerminationDate": null,
                "trChanges": null,
                "prStatus": 10,
                "prComplete": null,
                "vkmStatus": 10,
                "trStatus": 10,
                "userCreator": "U001502",
                "addedDate": "2020-07-30 12:35:33.0",
                "userChange": "KUVA-1124",
                "changeDate": "2020-07-30 12:35:33.0",
                "tlnumber": null,
                "mainImage": null,
                "track": null,
                "awsTunnus": "TIEKUVAT/TIE-4/TIEOSA-426/00004_426_2_06809_2_0-398447082.jpg",
                "awsUrl": "https://d28t77wkhtlfbl.cloudfront.net/smallpicture/TIEKUVAT/TIE-4/TIEOSA-426/00004_426_2_06809_2_0-398447082.jpg?token=BDJvz0gkeXlr4lbxjbRb3A==:e9XImceFWZh6Kvv0s/PdRkvuisYJFETOS69dVCLbXhjdXeghWV/vcBVA4olxwA0ykWY1SSQVnVFcbITz7mEzyw==",
                "awsThumbnailUrl": "https://d28t77wkhtlfbl.cloudfront.net/thumbnail/TIEKUVAT/TIE-4/TIEOSA-426/00004_426_2_06809_2_0-398447082.jpg?token=BDJvz0gkeXlr4lbxjbRb3A==:e9XImceFWZh6Kvv0s/PdRkvuisYJFETOS69dVCLbXhjdXeghWV/vcBVA4olxwA0ykWY1SSQVnVFcbITz7mEzyw==",
                "awsPictureUrl": "https://d28t77wkhtlfbl.cloudfront.net/picture/TIEKUVAT/TIE-4/TIEOSA-426/00004_426_2_06809_2_0-398447082.jpg?token=BDJvz0gkeXlr4lbxjbRb3A==:e9XImceFWZh6Kvv0s/PdRkvuisYJFETOS69dVCLbXhjdXeghWV/vcBVA4olxwA0ykWY1SSQVnVFcbITz7mEzyw==",
                "imagingJobId": "64",
                "displayType": 1,
                "stationId": null,
                "stationName": null,
                "greenBridgeId": null,
                "greenBridgeName": null,
                "sillariBridgeId": null,
                "sillariBridgeName": null,
                "__typename": "GQLImageInfo"
            },
            {
                "imageInfoId": "398357011",
                "imageId": "398447081.00",
                "historyDate": null,
                "fileName": "00004_426_2_06828_2_0.jpg",
                "id": "IP2020LAP125150",
                "typeImage": 2,
                "sourceSystem": 11,
                "ely": 14,
                "municipality": 241,
                "region": 19,
                "contractArea": 1432,
                "road": 4,
                "roadSection": 426,
                "distance": 6818,
                "trackCode": 1,
                "givenCoord": null,
                "xGivenCoord": 386002,
                "yGivenCoord": 7300994,
                "zGivenCoord": null,
                "calcCoord": null,
                "xCalcCoord": null,
                "yCalcCoord": null,
                "zCalcCoord": null,
                "definition": "Infrap tiekuvat 2020",
                "roadAddressDirection": 2,
                "descDirection": 141,
                "side": 0,
                "getMovedCenterLine": null,
                "date": "2020-06-26 03:12:05",
                "publicity": 11,
                "organization": null,
                "lastName": null,
                "firstName": null,
                "trTerminationDate": null,
                "trChanges": null,
                "prStatus": 10,
                "prComplete": null,
                "vkmStatus": 10,
                "trStatus": 10,
                "userCreator": "U001502",
                "addedDate": "2020-07-30 12:35:33.0",
                "userChange": "KUVA-1124",
                "changeDate": "2020-07-30 12:35:33.0",
                "tlnumber": null,
                "mainImage": null,
                "track": null,
                "awsTunnus": "TIEKUVAT/TIE-4/TIEOSA-426/00004_426_2_06828_2_0-398447081.jpg",
                "awsUrl": "https://d28t77wkhtlfbl.cloudfront.net/smallpicture/TIEKUVAT/TIE-4/TIEOSA-426/00004_426_2_06828_2_0-398447081.jpg?token=WYgFOKOMYkscrkoJ9sHI5g==:lCk1AnVkSDXq+rL9q4qXWuTduxlqe/NJpZ7Mjgw5OImAj4UVpbhUvqfT9tmordO75LTnXIzKq+zEa/YBlwSU+Q==",
                "awsThumbnailUrl": "https://d28t77wkhtlfbl.cloudfront.net/thumbnail/TIEKUVAT/TIE-4/TIEOSA-426/00004_426_2_06828_2_0-398447081.jpg?token=WYgFOKOMYkscrkoJ9sHI5g==:lCk1AnVkSDXq+rL9q4qXWuTduxlqe/NJpZ7Mjgw5OImAj4UVpbhUvqfT9tmordO75LTnXIzKq+zEa/YBlwSU+Q==",
                "awsPictureUrl": "https://d28t77wkhtlfbl.cloudfront.net/picture/TIEKUVAT/TIE-4/TIEOSA-426/00004_426_2_06828_2_0-398447081.jpg?token=WYgFOKOMYkscrkoJ9sHI5g==:lCk1AnVkSDXq+rL9q4qXWuTduxlqe/NJpZ7Mjgw5OImAj4UVpbhUvqfT9tmordO75LTnXIzKq+zEa/YBlwSU+Q==",
                "imagingJobId": "64",
                "displayType": 1,
                "stationId": null,
                "stationName": null,
                "greenBridgeId": null,
                "greenBridgeName": null,
                "sillariBridgeId": null,
                "sillariBridgeName": null,
                "__typename": "GQLImageInfo"
            },
            {
                "imageInfoId": "398357008",
                "imageId": "398447077.00",
                "historyDate": null,
                "fileName": "00004_426_2_06851_2_0.jpg",
                "id": "IP2020LAP125149",
                "typeImage": 2,
                "sourceSystem": 11,
                "ely": 14,
                "municipality": 241,
                "region": 19,
                "contractArea": 1432,
                "road": 4,
                "roadSection": 426,
                "distance": 6841,
                "trackCode": 1,
                "givenCoord": null,
                "xGivenCoord": 385989,
                "yGivenCoord": 7301013,
                "zGivenCoord": null,
                "calcCoord": null,
                "xCalcCoord": null,
                "yCalcCoord": null,
                "zCalcCoord": null,
                "definition": "Infrap tiekuvat 2020",
                "roadAddressDirection": 2,
                "descDirection": 141,
                "side": 0,
                "getMovedCenterLine": null,
                "date": "2020-06-26 03:12:04",
                "publicity": 11,
                "organization": null,
                "lastName": null,
                "firstName": null,
                "trTerminationDate": null,
                "trChanges": null,
                "prStatus": 10,
                "prComplete": null,
                "vkmStatus": 10,
                "trStatus": 10,
                "userCreator": "U001502",
                "addedDate": "2020-07-30 12:35:32.0",
                "userChange": "KUVA-1124",
                "changeDate": "2020-07-30 12:35:32.0",
                "tlnumber": null,
                "mainImage": null,
                "track": null,
                "awsTunnus": "TIEKUVAT/TIE-4/TIEOSA-426/00004_426_2_06851_2_0-398447077.jpg",
                "awsUrl": "https://d28t77wkhtlfbl.cloudfront.net/smallpicture/TIEKUVAT/TIE-4/TIEOSA-426/00004_426_2_06851_2_0-398447077.jpg?token=bQ/1pC7wpHNlv0C5oU9dSA==:vhUHm2XzxqeBtR8kHTdfbgTtKQ/cp8B8iPg4CAEAchzW69Ph6XnamPsoqN+DT2joSPUn+NDBkJVuTj4dchyYDw==",
                "awsThumbnailUrl": "https://d28t77wkhtlfbl.cloudfront.net/thumbnail/TIEKUVAT/TIE-4/TIEOSA-426/00004_426_2_06851_2_0-398447077.jpg?token=bQ/1pC7wpHNlv0C5oU9dSA==:vhUHm2XzxqeBtR8kHTdfbgTtKQ/cp8B8iPg4CAEAchzW69Ph6XnamPsoqN+DT2joSPUn+NDBkJVuTj4dchyYDw==",
                "awsPictureUrl": "https://d28t77wkhtlfbl.cloudfront.net/picture/TIEKUVAT/TIE-4/TIEOSA-426/00004_426_2_06851_2_0-398447077.jpg?token=bQ/1pC7wpHNlv0C5oU9dSA==:vhUHm2XzxqeBtR8kHTdfbgTtKQ/cp8B8iPg4CAEAchzW69Ph6XnamPsoqN+DT2joSPUn+NDBkJVuTj4dchyYDw==",
                "imagingJobId": "64",
                "displayType": 1,
                "stationId": null,
                "stationName": null,
                "greenBridgeId": null,
                "greenBridgeName": null,
                "sillariBridgeId": null,
                "sillariBridgeName": null,
                "__typename": "GQLImageInfo"
            },
            {
                "imageInfoId": "398356995",
                "imageId": "398447065.00",
                "historyDate": null,
                "fileName": "00004_426_2_06870_2_0.jpg",
                "id": "IP2020LAP125148",
                "typeImage": 2,
                "sourceSystem": 11,
                "ely": 14,
                "municipality": 241,
                "region": 19,
                "contractArea": 1432,
                "road": 4,
                "roadSection": 426,
                "distance": 6860,
                "trackCode": 1,
                "givenCoord": null,
                "xGivenCoord": 385978,
                "yGivenCoord": 7301028,
                "zGivenCoord": null,
                "calcCoord": null,
                "xCalcCoord": null,
                "yCalcCoord": null,
                "zCalcCoord": null,
                "definition": "Infrap tiekuvat 2020",
                "roadAddressDirection": 2,
                "descDirection": 141,
                "side": 0,
                "getMovedCenterLine": null,
                "date": "2020-06-26 03:12:03",
                "publicity": 11,
                "organization": null,
                "lastName": null,
                "firstName": null,
                "trTerminationDate": null,
                "trChanges": null,
                "prStatus": 10,
                "prComplete": null,
                "vkmStatus": 10,
                "trStatus": 10,
                "userCreator": "U001502",
                "addedDate": "2020-07-30 12:35:30.0",
                "userChange": "KUVA-1124",
                "changeDate": "2020-07-30 12:35:30.0",
                "tlnumber": null,
                "mainImage": null,
                "track": null,
                "awsTunnus": "TIEKUVAT/TIE-4/TIEOSA-426/00004_426_2_06870_2_0-398447065.jpg",
                "awsUrl": "https://d28t77wkhtlfbl.cloudfront.net/smallpicture/TIEKUVAT/TIE-4/TIEOSA-426/00004_426_2_06870_2_0-398447065.jpg?token=FvK9xReq0/XlSgHYKXCg8g==:ihU17zwd1uC5xixG7s5XWfFd8S1vAgYlU/3UzHgWDxr9/L66AprcXflH25gwLW3rfJypg60QhBVduN9yv+NkSw==",
                "awsThumbnailUrl": "https://d28t77wkhtlfbl.cloudfront.net/thumbnail/TIEKUVAT/TIE-4/TIEOSA-426/00004_426_2_06870_2_0-398447065.jpg?token=FvK9xReq0/XlSgHYKXCg8g==:ihU17zwd1uC5xixG7s5XWfFd8S1vAgYlU/3UzHgWDxr9/L66AprcXflH25gwLW3rfJypg60QhBVduN9yv+NkSw==",
                "awsPictureUrl": "https://d28t77wkhtlfbl.cloudfront.net/picture/TIEKUVAT/TIE-4/TIEOSA-426/00004_426_2_06870_2_0-398447065.jpg?token=FvK9xReq0/XlSgHYKXCg8g==:ihU17zwd1uC5xixG7s5XWfFd8S1vAgYlU/3UzHgWDxr9/L66AprcXflH25gwLW3rfJypg60QhBVduN9yv+NkSw==",
                "imagingJobId": "64",
                "displayType": 1,
                "stationId": null,
                "stationName": null,
                "greenBridgeId": null,
                "greenBridgeName": null,
                "sillariBridgeId": null,
                "sillariBridgeName": null,
                "__typename": "GQLImageInfo"
            },
            {
                "imageInfoId": "398356993",
                "imageId": "398447062.00",
                "historyDate": null,
                "fileName": "00004_426_2_06889_2_0.jpg",
                "id": "IP2020LAP125147",
                "typeImage": 2,
                "sourceSystem": 11,
                "ely": 14,
                "municipality": 241,
                "region": 19,
                "contractArea": 1432,
                "road": 4,
                "roadSection": 426,
                "distance": 6879,
                "trackCode": 1,
                "givenCoord": null,
                "xGivenCoord": 385966,
                "yGivenCoord": 7301044,
                "zGivenCoord": null,
                "calcCoord": null,
                "xCalcCoord": null,
                "yCalcCoord": null,
                "zCalcCoord": null,
                "definition": "Infrap tiekuvat 2020",
                "roadAddressDirection": 2,
                "descDirection": 141,
                "side": 0,
                "getMovedCenterLine": null,
                "date": "2020-06-26 03:12:02",
                "publicity": 11,
                "organization": null,
                "lastName": null,
                "firstName": null,
                "trTerminationDate": null,
                "trChanges": null,
                "prStatus": 10,
                "prComplete": null,
                "vkmStatus": 10,
                "trStatus": 10,
                "userCreator": "U001502",
                "addedDate": "2020-07-30 12:35:29.0",
                "userChange": "KUVA-1124",
                "changeDate": "2020-07-30 12:35:29.0",
                "tlnumber": null,
                "mainImage": null,
                "track": null,
                "awsTunnus": "TIEKUVAT/TIE-4/TIEOSA-426/00004_426_2_06889_2_0-398447062.jpg",
                "awsUrl": "https://d28t77wkhtlfbl.cloudfront.net/smallpicture/TIEKUVAT/TIE-4/TIEOSA-426/00004_426_2_06889_2_0-398447062.jpg?token=TH6tTn9QJ0DMYRpl9N0hdQ==:O1c9TNGMeaa72oCpXYkEwio4CQagLg1mSMadfwMxcCyPFuc4QZmaVoZ161qYnu5DXdsJOBv27QcG1LUQSg4FFw==",
                "awsThumbnailUrl": "https://d28t77wkhtlfbl.cloudfront.net/thumbnail/TIEKUVAT/TIE-4/TIEOSA-426/00004_426_2_06889_2_0-398447062.jpg?token=TH6tTn9QJ0DMYRpl9N0hdQ==:O1c9TNGMeaa72oCpXYkEwio4CQagLg1mSMadfwMxcCyPFuc4QZmaVoZ161qYnu5DXdsJOBv27QcG1LUQSg4FFw==",
                "awsPictureUrl": "https://d28t77wkhtlfbl.cloudfront.net/picture/TIEKUVAT/TIE-4/TIEOSA-426/00004_426_2_06889_2_0-398447062.jpg?token=TH6tTn9QJ0DMYRpl9N0hdQ==:O1c9TNGMeaa72oCpXYkEwio4CQagLg1mSMadfwMxcCyPFuc4QZmaVoZ161qYnu5DXdsJOBv27QcG1LUQSg4FFw==",
                "imagingJobId": "64",
                "displayType": 1,
                "stationId": null,
                "stationName": null,
                "greenBridgeId": null,
                "greenBridgeName": null,
                "sillariBridgeId": null,
                "sillariBridgeName": null,
                "__typename": "GQLImageInfo"
            },
            {
                "imageInfoId": "398356989",
                "imageId": "398447059.00",
                "historyDate": null,
                "fileName": "00004_426_2_06909_2_0.jpg",
                "id": "IP2020LAP125146",
                "typeImage": 2,
                "sourceSystem": 11,
                "ely": 14,
                "municipality": 241,
                "region": 19,
                "contractArea": 1432,
                "road": 4,
                "roadSection": 426,
                "distance": 6898,
                "trackCode": 1,
                "givenCoord": null,
                "xGivenCoord": 385955,
                "yGivenCoord": 7301059,
                "zGivenCoord": null,
                "calcCoord": null,
                "xCalcCoord": null,
                "yCalcCoord": null,
                "zCalcCoord": null,
                "definition": "Infrap tiekuvat 2020",
                "roadAddressDirection": 2,
                "descDirection": 140,
                "side": 0,
                "getMovedCenterLine": null,
                "date": "2020-06-26 03:12:01",
                "publicity": 11,
                "organization": null,
                "lastName": null,
                "firstName": null,
                "trTerminationDate": null,
                "trChanges": null,
                "prStatus": 10,
                "prComplete": null,
                "vkmStatus": 10,
                "trStatus": 10,
                "userCreator": "U001502",
                "addedDate": "2020-07-30 12:35:29.0",
                "userChange": "KUVA-1124",
                "changeDate": "2020-07-30 12:35:29.0",
                "tlnumber": null,
                "mainImage": null,
                "track": null,
                "awsTunnus": "TIEKUVAT/TIE-4/TIEOSA-426/00004_426_2_06909_2_0-398447059.jpg",
                "awsUrl": "https://d28t77wkhtlfbl.cloudfront.net/smallpicture/TIEKUVAT/TIE-4/TIEOSA-426/00004_426_2_06909_2_0-398447059.jpg?token=ygQsQFTy0Mb86IQIj3l4sg==:E9WtGPQpPMJpZ7WFLoutSKb263pieY5L7AYKZ6Vd+6VlnT5l8ox072ngF506D39aJZzIGirRFKRSRN20sUoXuA==",
                "awsThumbnailUrl": "https://d28t77wkhtlfbl.cloudfront.net/thumbnail/TIEKUVAT/TIE-4/TIEOSA-426/00004_426_2_06909_2_0-398447059.jpg?token=ygQsQFTy0Mb86IQIj3l4sg==:E9WtGPQpPMJpZ7WFLoutSKb263pieY5L7AYKZ6Vd+6VlnT5l8ox072ngF506D39aJZzIGirRFKRSRN20sUoXuA==",
                "awsPictureUrl": "https://d28t77wkhtlfbl.cloudfront.net/picture/TIEKUVAT/TIE-4/TIEOSA-426/00004_426_2_06909_2_0-398447059.jpg?token=ygQsQFTy0Mb86IQIj3l4sg==:E9WtGPQpPMJpZ7WFLoutSKb263pieY5L7AYKZ6Vd+6VlnT5l8ox072ngF506D39aJZzIGirRFKRSRN20sUoXuA==",
                "imagingJobId": "64",
                "displayType": 1,
                "stationId": null,
                "stationName": null,
                "greenBridgeId": null,
                "greenBridgeName": null,
                "sillariBridgeId": null,
                "sillariBridgeName": null,
                "__typename": "GQLImageInfo"
            },
            {
                "imageInfoId": "398356969",
                "imageId": "398447037.00",
                "historyDate": null,
                "fileName": "00004_426_2_06928_2_0.jpg",
                "id": "IP2020LAP125145",
                "typeImage": 2,
                "sourceSystem": 11,
                "ely": 14,
                "municipality": 241,
                "region": 19,
                "contractArea": 1432,
                "road": 4,
                "roadSection": 426,
                "distance": 6918,
                "trackCode": 1,
                "givenCoord": null,
                "xGivenCoord": 385943,
                "yGivenCoord": 7301074,
                "zGivenCoord": null,
                "calcCoord": null,
                "xCalcCoord": null,
                "yCalcCoord": null,
                "zCalcCoord": null,
                "definition": "Infrap tiekuvat 2020",
                "roadAddressDirection": 2,
                "descDirection": 140,
                "side": 0,
                "getMovedCenterLine": null,
                "date": "2020-06-26 03:12:00",
                "publicity": 11,
                "organization": null,
                "lastName": null,
                "firstName": null,
                "trTerminationDate": null,
                "trChanges": null,
                "prStatus": 10,
                "prComplete": null,
                "vkmStatus": 10,
                "trStatus": 10,
                "userCreator": "U001502",
                "addedDate": "2020-07-30 12:35:26.0",
                "userChange": "KUVA-1124",
                "changeDate": "2020-07-30 12:35:26.0",
                "tlnumber": null,
                "mainImage": null,
                "track": null,
                "awsTunnus": "TIEKUVAT/TIE-4/TIEOSA-426/00004_426_2_06928_2_0-398447037.jpg",
                "awsUrl": "https://d28t77wkhtlfbl.cloudfront.net/smallpicture/TIEKUVAT/TIE-4/TIEOSA-426/00004_426_2_06928_2_0-398447037.jpg?token=l8UZzrUzg8XeJgWTb5lCNw==:jsbI1QtI5AlNTlnMp3zUspqHzm7M69oHtoVxNWgieULUm8ah/McIhXSZ8XGB0DWaqhw9+nZC26jY5AezY4fzLg==",
                "awsThumbnailUrl": "https://d28t77wkhtlfbl.cloudfront.net/thumbnail/TIEKUVAT/TIE-4/TIEOSA-426/00004_426_2_06928_2_0-398447037.jpg?token=l8UZzrUzg8XeJgWTb5lCNw==:jsbI1QtI5AlNTlnMp3zUspqHzm7M69oHtoVxNWgieULUm8ah/McIhXSZ8XGB0DWaqhw9+nZC26jY5AezY4fzLg==",
                "awsPictureUrl": "https://d28t77wkhtlfbl.cloudfront.net/picture/TIEKUVAT/TIE-4/TIEOSA-426/00004_426_2_06928_2_0-398447037.jpg?token=l8UZzrUzg8XeJgWTb5lCNw==:jsbI1QtI5AlNTlnMp3zUspqHzm7M69oHtoVxNWgieULUm8ah/McIhXSZ8XGB0DWaqhw9+nZC26jY5AezY4fzLg==",
                "imagingJobId": "64",
                "displayType": 1,
                "stationId": null,
                "stationName": null,
                "greenBridgeId": null,
                "greenBridgeName": null,
                "sillariBridgeId": null,
                "sillariBridgeName": null,
                "__typename": "GQLImageInfo"
            },
            {
                "imageInfoId": "398356964",
                "imageId": "398447033.00",
                "historyDate": null,
                "fileName": "00004_426_2_06947_2_0.jpg",
                "id": "IP2020LAP125144",
                "typeImage": 2,
                "sourceSystem": 11,
                "ely": 14,
                "municipality": 241,
                "region": 19,
                "contractArea": 1432,
                "road": 4,
                "roadSection": 426,
                "distance": 6937,
                "trackCode": 1,
                "givenCoord": null,
                "xGivenCoord": 385932,
                "yGivenCoord": 7301090,
                "zGivenCoord": null,
                "calcCoord": null,
                "xCalcCoord": null,
                "yCalcCoord": null,
                "zCalcCoord": null,
                "definition": "Infrap tiekuvat 2020",
                "roadAddressDirection": 2,
                "descDirection": 140,
                "side": 0,
                "getMovedCenterLine": null,
                "date": "2020-06-26 03:11:59",
                "publicity": 11,
                "organization": null,
                "lastName": null,
                "firstName": null,
                "trTerminationDate": null,
                "trChanges": null,
                "prStatus": 10,
                "prComplete": null,
                "vkmStatus": 10,
                "trStatus": 10,
                "userCreator": "U001502",
                "addedDate": "2020-07-30 12:35:25.0",
                "userChange": "KUVA-1124",
                "changeDate": "2020-07-30 12:35:25.0",
                "tlnumber": null,
                "mainImage": null,
                "track": null,
                "awsTunnus": "TIEKUVAT/TIE-4/TIEOSA-426/00004_426_2_06947_2_0-398447033.jpg",
                "awsUrl": "https://d28t77wkhtlfbl.cloudfront.net/smallpicture/TIEKUVAT/TIE-4/TIEOSA-426/00004_426_2_06947_2_0-398447033.jpg?token=l6eISHjUXvii0Cz9Yizenw==:ZrEKTiKx1FmJBHD8JzEAQ9oS8JR4bt05wDUiQckKjtyN7bOZrkQItJAHivdh+fZVfx1GEq3S2gzbYu805x/pBw==",
                "awsThumbnailUrl": "https://d28t77wkhtlfbl.cloudfront.net/thumbnail/TIEKUVAT/TIE-4/TIEOSA-426/00004_426_2_06947_2_0-398447033.jpg?token=l6eISHjUXvii0Cz9Yizenw==:ZrEKTiKx1FmJBHD8JzEAQ9oS8JR4bt05wDUiQckKjtyN7bOZrkQItJAHivdh+fZVfx1GEq3S2gzbYu805x/pBw==",
                "awsPictureUrl": "https://d28t77wkhtlfbl.cloudfront.net/picture/TIEKUVAT/TIE-4/TIEOSA-426/00004_426_2_06947_2_0-398447033.jpg?token=l6eISHjUXvii0Cz9Yizenw==:ZrEKTiKx1FmJBHD8JzEAQ9oS8JR4bt05wDUiQckKjtyN7bOZrkQItJAHivdh+fZVfx1GEq3S2gzbYu805x/pBw==",
                "imagingJobId": "64",
                "displayType": 1,
                "stationId": null,
                "stationName": null,
                "greenBridgeId": null,
                "greenBridgeName": null,
                "sillariBridgeId": null,
                "sillariBridgeName": null,
                "__typename": "GQLImageInfo"
            },
            {
                "imageInfoId": "398356962",
                "imageId": "398447031.00",
                "historyDate": null,
                "fileName": "00004_426_2_06966_2_0.jpg",
                "id": "IP2020LAP125143",
                "typeImage": 2,
                "sourceSystem": 11,
                "ely": 14,
                "municipality": 241,
                "region": 19,
                "contractArea": 1432,
                "road": 4,
                "roadSection": 426,
                "distance": 6956,
                "trackCode": 1,
                "givenCoord": null,
                "xGivenCoord": 385920,
                "yGivenCoord": 7301105,
                "zGivenCoord": null,
                "calcCoord": null,
                "xCalcCoord": null,
                "yCalcCoord": null,
                "zCalcCoord": null,
                "definition": "Infrap tiekuvat 2020",
                "roadAddressDirection": 2,
                "descDirection": 140,
                "side": 0,
                "getMovedCenterLine": null,
                "date": "2020-06-26 03:11:58",
                "publicity": 11,
                "organization": null,
                "lastName": null,
                "firstName": null,
                "trTerminationDate": null,
                "trChanges": null,
                "prStatus": 10,
                "prComplete": null,
                "vkmStatus": 10,
                "trStatus": 10,
                "userCreator": "U001502",
                "addedDate": "2020-07-30 12:35:25.0",
                "userChange": "KUVA-1124",
                "changeDate": "2020-07-30 12:35:25.0",
                "tlnumber": null,
                "mainImage": null,
                "track": null,
                "awsTunnus": "TIEKUVAT/TIE-4/TIEOSA-426/00004_426_2_06966_2_0-398447031.jpg",
                "awsUrl": "https://d28t77wkhtlfbl.cloudfront.net/smallpicture/TIEKUVAT/TIE-4/TIEOSA-426/00004_426_2_06966_2_0-398447031.jpg?token=aHwoWy+dLU9aUYWfV2VptQ==:s92MfLEdQTTb2MQT3GehwKKNQS4/GYu9pg0TuUspa8eFUU5K1JGIUtLKUDOvTB0yZjvGBFxo+RwjPwEOiyorjg==",
                "awsThumbnailUrl": "https://d28t77wkhtlfbl.cloudfront.net/thumbnail/TIEKUVAT/TIE-4/TIEOSA-426/00004_426_2_06966_2_0-398447031.jpg?token=aHwoWy+dLU9aUYWfV2VptQ==:s92MfLEdQTTb2MQT3GehwKKNQS4/GYu9pg0TuUspa8eFUU5K1JGIUtLKUDOvTB0yZjvGBFxo+RwjPwEOiyorjg==",
                "awsPictureUrl": "https://d28t77wkhtlfbl.cloudfront.net/picture/TIEKUVAT/TIE-4/TIEOSA-426/00004_426_2_06966_2_0-398447031.jpg?token=aHwoWy+dLU9aUYWfV2VptQ==:s92MfLEdQTTb2MQT3GehwKKNQS4/GYu9pg0TuUspa8eFUU5K1JGIUtLKUDOvTB0yZjvGBFxo+RwjPwEOiyorjg==",
                "imagingJobId": "64",
                "displayType": 1,
                "stationId": null,
                "stationName": null,
                "greenBridgeId": null,
                "greenBridgeName": null,
                "sillariBridgeId": null,
                "sillariBridgeName": null,
                "__typename": "GQLImageInfo"
            },
            {
                "imageInfoId": "398356936",
                "imageId": "398447005.00",
                "historyDate": null,
                "fileName": "00004_426_2_06990_2_0.jpg",
                "id": "IP2020LAP125142",
                "typeImage": 2,
                "sourceSystem": 11,
                "ely": 14,
                "municipality": 241,
                "region": 19,
                "contractArea": 1432,
                "road": 4,
                "roadSection": 426,
                "distance": 6980,
                "trackCode": 1,
                "givenCoord": null,
                "xGivenCoord": 385906,
                "yGivenCoord": 7301124,
                "zGivenCoord": null,
                "calcCoord": null,
                "xCalcCoord": null,
                "yCalcCoord": null,
                "zCalcCoord": null,
                "definition": "Infrap tiekuvat 2020",
                "roadAddressDirection": 2,
                "descDirection": 140,
                "side": 0,
                "getMovedCenterLine": null,
                "date": "2020-06-26 03:11:56",
                "publicity": 11,
                "organization": null,
                "lastName": null,
                "firstName": null,
                "trTerminationDate": null,
                "trChanges": null,
                "prStatus": 10,
                "prComplete": null,
                "vkmStatus": 10,
                "trStatus": 10,
                "userCreator": "U001502",
                "addedDate": "2020-07-30 12:35:22.0",
                "userChange": "KUVA-1124",
                "changeDate": "2020-07-30 12:35:22.0",
                "tlnumber": null,
                "mainImage": null,
                "track": null,
                "awsTunnus": "TIEKUVAT/TIE-4/TIEOSA-426/00004_426_2_06990_2_0-398447005.jpg",
                "awsUrl": "https://d28t77wkhtlfbl.cloudfront.net/smallpicture/TIEKUVAT/TIE-4/TIEOSA-426/00004_426_2_06990_2_0-398447005.jpg?token=Zv3f1+U7y93sUpuZWzkxGA==:qbNKj57nfXoAPoLHxZ6PzKSyv5UUok815+m+f/hIzmd7ek1Dx5vcHeTpIDO3nc2dXpdnmpRUgofXn1W+kUgs/w==",
                "awsThumbnailUrl": "https://d28t77wkhtlfbl.cloudfront.net/thumbnail/TIEKUVAT/TIE-4/TIEOSA-426/00004_426_2_06990_2_0-398447005.jpg?token=Zv3f1+U7y93sUpuZWzkxGA==:qbNKj57nfXoAPoLHxZ6PzKSyv5UUok815+m+f/hIzmd7ek1Dx5vcHeTpIDO3nc2dXpdnmpRUgofXn1W+kUgs/w==",
                "awsPictureUrl": "https://d28t77wkhtlfbl.cloudfront.net/picture/TIEKUVAT/TIE-4/TIEOSA-426/00004_426_2_06990_2_0-398447005.jpg?token=Zv3f1+U7y93sUpuZWzkxGA==:qbNKj57nfXoAPoLHxZ6PzKSyv5UUok815+m+f/hIzmd7ek1Dx5vcHeTpIDO3nc2dXpdnmpRUgofXn1W+kUgs/w==",
                "imagingJobId": "64",
                "displayType": 1,
                "stationId": null,
                "stationName": null,
                "greenBridgeId": null,
                "greenBridgeName": null,
                "sillariBridgeId": null,
                "sillariBridgeName": null,
                "__typename": "GQLImageInfo"
            },
            {
                "imageInfoId": "398356934",
                "imageId": "398447003.00",
                "historyDate": null,
                "fileName": "00004_426_2_07009_2_0.jpg",
                "id": "IP2020LAP125141",
                "typeImage": 2,
                "sourceSystem": 11,
                "ely": 14,
                "municipality": 241,
                "region": 19,
                "contractArea": 1432,
                "road": 4,
                "roadSection": 426,
                "distance": 6998,
                "trackCode": 1,
                "givenCoord": null,
                "xGivenCoord": 385895,
                "yGivenCoord": 7301139,
                "zGivenCoord": null,
                "calcCoord": null,
                "xCalcCoord": null,
                "yCalcCoord": null,
                "zCalcCoord": null,
                "definition": "Infrap tiekuvat 2020",
                "roadAddressDirection": 2,
                "descDirection": 140,
                "side": 0,
                "getMovedCenterLine": null,
                "date": "2020-06-26 03:11:55",
                "publicity": 11,
                "organization": null,
                "lastName": null,
                "firstName": null,
                "trTerminationDate": null,
                "trChanges": null,
                "prStatus": 10,
                "prComplete": null,
                "vkmStatus": 10,
                "trStatus": 10,
                "userCreator": "U001502",
                "addedDate": "2020-07-30 12:35:21.0",
                "userChange": "KUVA-1124",
                "changeDate": "2020-07-30 12:35:21.0",
                "tlnumber": null,
                "mainImage": null,
                "track": null,
                "awsTunnus": "TIEKUVAT/TIE-4/TIEOSA-426/00004_426_2_07009_2_0-398447003.jpg",
                "awsUrl": "https://d28t77wkhtlfbl.cloudfront.net/smallpicture/TIEKUVAT/TIE-4/TIEOSA-426/00004_426_2_07009_2_0-398447003.jpg?token=DuWk9JdCC6jn+qjSUomPmg==:QatLSm2Pou0QWG8D3tFPNTdHm5liQa+9q5vZ86OMbKDBfpa4yPCJhRup9EZbKhIu/uwTAr5F1XOHZXhPbad3aA==",
                "awsThumbnailUrl": "https://d28t77wkhtlfbl.cloudfront.net/thumbnail/TIEKUVAT/TIE-4/TIEOSA-426/00004_426_2_07009_2_0-398447003.jpg?token=DuWk9JdCC6jn+qjSUomPmg==:QatLSm2Pou0QWG8D3tFPNTdHm5liQa+9q5vZ86OMbKDBfpa4yPCJhRup9EZbKhIu/uwTAr5F1XOHZXhPbad3aA==",
                "awsPictureUrl": "https://d28t77wkhtlfbl.cloudfront.net/picture/TIEKUVAT/TIE-4/TIEOSA-426/00004_426_2_07009_2_0-398447003.jpg?token=DuWk9JdCC6jn+qjSUomPmg==:QatLSm2Pou0QWG8D3tFPNTdHm5liQa+9q5vZ86OMbKDBfpa4yPCJhRup9EZbKhIu/uwTAr5F1XOHZXhPbad3aA==",
                "imagingJobId": "64",
                "displayType": 1,
                "stationId": null,
                "stationName": null,
                "greenBridgeId": null,
                "greenBridgeName": null,
                "sillariBridgeId": null,
                "sillariBridgeName": null,
                "__typename": "GQLImageInfo"
            },
            {
                "imageInfoId": "398356925",
                "imageId": "398446995.00",
                "historyDate": null,
                "fileName": "00004_426_2_07043_2_0.jpg",
                "id": "IP2020LAP125139",
                "typeImage": 2,
                "sourceSystem": 11,
                "ely": 14,
                "municipality": 241,
                "region": 19,
                "contractArea": 1432,
                "road": 4,
                "roadSection": 426,
                "distance": 7033,
                "trackCode": 1,
                "givenCoord": null,
                "xGivenCoord": 385874,
                "yGivenCoord": 7301166,
                "zGivenCoord": null,
                "calcCoord": null,
                "xCalcCoord": null,
                "yCalcCoord": null,
                "zCalcCoord": null,
                "definition": "Infrap tiekuvat 2020",
                "roadAddressDirection": 2,
                "descDirection": 140,
                "side": 0,
                "getMovedCenterLine": null,
                "date": "2020-06-26 03:11:54",
                "publicity": 11,
                "organization": null,
                "lastName": null,
                "firstName": null,
                "trTerminationDate": null,
                "trChanges": null,
                "prStatus": 10,
                "prComplete": null,
                "vkmStatus": 10,
                "trStatus": 10,
                "userCreator": "U001502",
                "addedDate": "2020-07-30 12:35:18.0",
                "userChange": "KUVA-1124",
                "changeDate": "2020-07-30 12:35:18.0",
                "tlnumber": null,
                "mainImage": null,
                "track": null,
                "awsTunnus": "TIEKUVAT/TIE-4/TIEOSA-426/00004_426_2_07043_2_0-398446995.jpg",
                "awsUrl": "https://d28t77wkhtlfbl.cloudfront.net/smallpicture/TIEKUVAT/TIE-4/TIEOSA-426/00004_426_2_07043_2_0-398446995.jpg?token=YUxf4+4GCZrYZ4XtqVIMFA==:+Y2hj9sXtPXOA3B6MmN05yG2bSNpp3thGRV6cfRc5P147gO0VWTVAOE6MbQRF0tTFgB4204ESknYTL3XOBoLFw==",
                "awsThumbnailUrl": "https://d28t77wkhtlfbl.cloudfront.net/thumbnail/TIEKUVAT/TIE-4/TIEOSA-426/00004_426_2_07043_2_0-398446995.jpg?token=YUxf4+4GCZrYZ4XtqVIMFA==:+Y2hj9sXtPXOA3B6MmN05yG2bSNpp3thGRV6cfRc5P147gO0VWTVAOE6MbQRF0tTFgB4204ESknYTL3XOBoLFw==",
                "awsPictureUrl": "https://d28t77wkhtlfbl.cloudfront.net/picture/TIEKUVAT/TIE-4/TIEOSA-426/00004_426_2_07043_2_0-398446995.jpg?token=YUxf4+4GCZrYZ4XtqVIMFA==:+Y2hj9sXtPXOA3B6MmN05yG2bSNpp3thGRV6cfRc5P147gO0VWTVAOE6MbQRF0tTFgB4204ESknYTL3XOBoLFw==",
                "imagingJobId": "64",
                "displayType": 1,
                "stationId": null,
                "stationName": null,
                "greenBridgeId": null,
                "greenBridgeName": null,
                "sillariBridgeId": null,
                "sillariBridgeName": null,
                "__typename": "GQLImageInfo"
            }
        ]
    }
}